whn_marketplace/__init__.py
whn_marketplace/assets.py
whn_marketplace-0.0.1.dist-info/LICENSE
whn_marketplace-0.0.1.dist-info/METADATA
whn_marketplace-0.0.1.dist-info/WHEEL
whn_marketplace-0.0.1.dist-info/top_level.txt
whn_marketplace-0.0.1.dist-info/RECORD
