Metadata-Version: 2.1
Name: whn-marketplace
Version: 0.0.1
Summary: Consolidates data models into one package to be shared between microservices and server
Author-email: Andrew Martinez <martinezdynamics@gmail.com>
Project-URL: Homepage, https://github.com/drewski90/What-Happens-Next-SDK
Classifier: Programming Language :: Python :: 3
Classifier: License :: OSI Approved :: MIT License
Classifier: Operating System :: OS Independent
Requires-Python: >=3.7
License-File: LICENSE
